{"nodes": [{"id": "page", "label": "page.tsx", "file_type": "code", "source_file": "frontend\\src\\app\\dashboard\\semantic\\page.tsx", "source_location": "L1"}, {"id": "page_loadrules", "label": "loadRules()", "file_type": "code", "source_file": "frontend\\src\\app\\dashboard\\semantic\\page.tsx", "source_location": "L42"}, {"id": "page_handleadd", "label": "handleAdd()", "file_type": "code", "source_file": "frontend\\src\\app\\dashboard\\semantic\\page.tsx", "source_location": "L76"}, {"id": "page_handledelete", "label": "handleDelete()", "file_type": "code", "source_file": "frontend\\src\\app\\dashboard\\semantic\\page.tsx", "source_location": "L99"}, {"id": "page_handleaddexample", "label": "handleAddExample()", "file_type": "code", "source_file": "frontend\\src\\app\\dashboard\\semantic\\page.tsx", "source_location": "L108"}], "edges": [{"source": "page", "target": "react", "relation": "imports_from", "confidence": "EXTRACTED", "source_file": "frontend\\src\\app\\dashboard\\semantic\\page.tsx", "source_location": "L3", "weight": 1.0}, {"source": "page", "target": "navigation", "relation": "imports_from", "confidence": "EXTRACTED", "source_file": "frontend\\src\\app\\dashboard\\semantic\\page.tsx", "source_location": "L4", "weight": 1.0}, {"source": "page", "target": "lucide_react", "relation": "imports_from", "confidence": "EXTRACTED", "source_file": "frontend\\src\\app\\dashboard\\semantic\\page.tsx", "source_location": "L5", "weight": 1.0}, {"source": "page", "target": "button", "relation": "imports_from", "confidence": "EXTRACTED", "source_file": "frontend\\src\\app\\dashboard\\semantic\\page.tsx", "source_location": "L6", "weight": 1.0}, {"source": "page", "target": "dashboardshell", "relation": "imports_from", "confidence": "EXTRACTED", "source_file": "frontend\\src\\app\\dashboard\\semantic\\page.tsx", "source_location": "L7", "weight": 1.0}, {"source": "page", "target": "page_loadrules", "relation": "contains", "confidence": "EXTRACTED", "source_file": "frontend\\src\\app\\dashboard\\semantic\\page.tsx", "source_location": "L42", "weight": 1.0}, {"source": "page", "target": "page_handleadd", "relation": "contains", "confidence": "EXTRACTED", "source_file": "frontend\\src\\app\\dashboard\\semantic\\page.tsx", "source_location": "L76", "weight": 1.0}, {"source": "page", "target": "page_handledelete", "relation": "contains", "confidence": "EXTRACTED", "source_file": "frontend\\src\\app\\dashboard\\semantic\\page.tsx", "source_location": "L99", "weight": 1.0}, {"source": "page", "target": "page_handleaddexample", "relation": "contains", "confidence": "EXTRACTED", "source_file": "frontend\\src\\app\\dashboard\\semantic\\page.tsx", "source_location": "L108", "weight": 1.0}, {"source": "page_handleadd", "target": "page_loadrules", "relation": "calls", "confidence": "EXTRACTED", "source_file": "frontend\\src\\app\\dashboard\\semantic\\page.tsx", "source_location": "L86", "weight": 1.0}, {"source": "page_handledelete", "target": "page_loadrules", "relation": "calls", "confidence": "EXTRACTED", "source_file": "frontend\\src\\app\\dashboard\\semantic\\page.tsx", "source_location": "L102", "weight": 1.0}, {"source": "page_handleaddexample", "target": "page_loadrules", "relation": "calls", "confidence": "EXTRACTED", "source_file": "frontend\\src\\app\\dashboard\\semantic\\page.tsx", "source_location": "L117", "weight": 1.0}]}